{
    "name": "UserSeedPivot",
    "line": 5,
    "short_desc": "",
    "long_desc": "",
    "hint": null,
    "tags": [],
    "namespace": "",
    "file": "\/home\/vagrant\/repos\/clipgui\/database\/seeds\/UserSeedPivot.php",
    "relative_file": null,
    "hash": "508ab5b42a811c60e5932383244a58d3c516e1d1",
    "parent": "Illuminate\\Database\\Seeder",
    "modifiers": 0,
    "is_trait": false,
    "is_interface": false,
    "aliases": {
        "StreamHandler": "Monolog\\Handler\\StreamHandler",
        "Schema": "Illuminate\\Support\\Facades\\Schema",
        "Blueprint": "Illuminate\\Database\\Schema\\Blueprint",
        "Migration": "Illuminate\\Database\\Migrations\\Migration",
        "Seeder": "Illuminate\\Database\\Seeder"
    },
    "errors": [],
    "interfaces": [],
    "traits": [],
    "properties": [],
    "methods": {
        "run": {
            "name": "run",
            "line": 12,
            "short_desc": "Run the database seeds.",
            "long_desc": "",
            "hint": [
                [
                    "void",
                    false
                ]
            ],
            "hint_desc": "",
            "tags": [],
            "modifiers": 1,
            "is_by_ref": "",
            "exceptions": [],
            "errors": [],
            "parameters": []
        }
    },
    "constants": []
}