{
    "name": "App\\Http\\Controllers\\Admin\\ProductsController",
    "line": 12,
    "short_desc": "",
    "long_desc": "",
    "hint": null,
    "tags": [],
    "namespace": "App\\Http\\Controllers\\Admin",
    "file": "\/home\/vagrant\/repos\/clipgui\/app\/Http\/Controllers\/Admin\/ProductsController.php",
    "relative_file": null,
    "hash": "d0e395491905feb01fcf63e803db610a2fcbe08d",
    "parent": "App\\Http\\Controllers\\Controller",
    "modifiers": 0,
    "is_trait": false,
    "is_interface": false,
    "aliases": {
        "Product": "App\\Product",
        "Request": "Illuminate\\Http\\Request",
        "Gate": "Illuminate\\Support\\Facades\\Gate",
        "Controller": "App\\Http\\Controllers\\Controller",
        "StoreProductsRequest": "App\\Http\\Requests\\Admin\\StoreProductsRequest",
        "UpdateProductsRequest": "App\\Http\\Requests\\Admin\\UpdateProductsRequest"
    },
    "errors": [],
    "interfaces": [],
    "traits": [],
    "properties": [],
    "methods": {
        "index": {
            "name": "index",
            "line": 19,
            "short_desc": "Display a listing of Product.",
            "long_desc": "",
            "hint": [
                [
                    "\\Illuminate\\Http\\Response",
                    false
                ]
            ],
            "hint_desc": "",
            "tags": [],
            "modifiers": 1,
            "is_by_ref": "",
            "exceptions": [],
            "errors": [],
            "parameters": []
        },
        "create": {
            "name": "create",
            "line": 43,
            "short_desc": "Show the form for creating new Product.",
            "long_desc": "",
            "hint": [
                [
                    "\\Illuminate\\Http\\Response",
                    false
                ]
            ],
            "hint_desc": "",
            "tags": [],
            "modifiers": 1,
            "is_by_ref": "",
            "exceptions": [],
            "errors": [],
            "parameters": []
        },
        "store": {
            "name": "store",
            "line": 57,
            "short_desc": "Store a newly created Product in storage.",
            "long_desc": "",
            "hint": [
                [
                    "\\Illuminate\\Http\\Response",
                    false
                ]
            ],
            "hint_desc": "",
            "tags": [],
            "modifiers": 1,
            "is_by_ref": "",
            "exceptions": [],
            "errors": [],
            "parameters": {
                "request": {
                    "name": "request",
                    "line": 57,
                    "short_desc": "",
                    "long_desc": null,
                    "hint": [
                        [
                            "\\App\\Http\\Requests\\Admin\\StoreProductsRequest",
                            false
                        ]
                    ],
                    "tags": [],
                    "modifiers": {
                        "nodeType": "Name_FullyQualified",
                        "parts": [
                            "App",
                            "Http",
                            "Requests",
                            "Admin",
                            "StoreProductsRequest"
                        ],
                        "attributes": {
                            "startLine": 57,
                            "endLine": 57
                        }
                    },
                    "default": null,
                    "variadic": false,
                    "is_by_ref": false
                }
            }
        },
        "edit": {
            "name": "edit",
            "line": 76,
            "short_desc": "Show the form for editing Product.",
            "long_desc": "",
            "hint": [
                [
                    "\\Illuminate\\Http\\Response",
                    false
                ]
            ],
            "hint_desc": "",
            "tags": [],
            "modifiers": 1,
            "is_by_ref": "",
            "exceptions": [],
            "errors": [],
            "parameters": {
                "id": {
                    "name": "id",
                    "line": 76,
                    "short_desc": "",
                    "long_desc": null,
                    "hint": [
                        [
                            "int",
                            false
                        ]
                    ],
                    "tags": [],
                    "modifiers": null,
                    "default": null,
                    "variadic": false,
                    "is_by_ref": false
                }
            }
        },
        "update": {
            "name": "update",
            "line": 93,
            "short_desc": "Update Product in storage.",
            "long_desc": "",
            "hint": [
                [
                    "\\Illuminate\\Http\\Response",
                    false
                ]
            ],
            "hint_desc": "",
            "tags": [],
            "modifiers": 1,
            "is_by_ref": "",
            "exceptions": [],
            "errors": [],
            "parameters": {
                "request": {
                    "name": "request",
                    "line": 93,
                    "short_desc": "",
                    "long_desc": null,
                    "hint": [
                        [
                            "\\App\\Http\\Requests\\Admin\\UpdateProductsRequest",
                            false
                        ]
                    ],
                    "tags": [],
                    "modifiers": {
                        "nodeType": "Name_FullyQualified",
                        "parts": [
                            "App",
                            "Http",
                            "Requests",
                            "Admin",
                            "UpdateProductsRequest"
                        ],
                        "attributes": {
                            "startLine": 93,
                            "endLine": 93
                        }
                    },
                    "default": null,
                    "variadic": false,
                    "is_by_ref": false
                },
                "id": {
                    "name": "id",
                    "line": 93,
                    "short_desc": "",
                    "long_desc": null,
                    "hint": [
                        [
                            "int",
                            false
                        ]
                    ],
                    "tags": [],
                    "modifiers": null,
                    "default": null,
                    "variadic": false,
                    "is_by_ref": false
                }
            }
        },
        "show": {
            "name": "show",
            "line": 113,
            "short_desc": "Display Product.",
            "long_desc": "",
            "hint": [
                [
                    "\\Illuminate\\Http\\Response",
                    false
                ]
            ],
            "hint_desc": "",
            "tags": [],
            "modifiers": 1,
            "is_by_ref": "",
            "exceptions": [],
            "errors": [],
            "parameters": {
                "id": {
                    "name": "id",
                    "line": 113,
                    "short_desc": "",
                    "long_desc": null,
                    "hint": [
                        [
                            "int",
                            false
                        ]
                    ],
                    "tags": [],
                    "modifiers": null,
                    "default": null,
                    "variadic": false,
                    "is_by_ref": false
                }
            }
        },
        "destroy": {
            "name": "destroy",
            "line": 132,
            "short_desc": "Remove Product from storage.",
            "long_desc": "",
            "hint": [
                [
                    "\\Illuminate\\Http\\Response",
                    false
                ]
            ],
            "hint_desc": "",
            "tags": [],
            "modifiers": 1,
            "is_by_ref": "",
            "exceptions": [],
            "errors": [],
            "parameters": {
                "id": {
                    "name": "id",
                    "line": 132,
                    "short_desc": "",
                    "long_desc": null,
                    "hint": [
                        [
                            "int",
                            false
                        ]
                    ],
                    "tags": [],
                    "modifiers": null,
                    "default": null,
                    "variadic": false,
                    "is_by_ref": false
                }
            }
        },
        "massDestroy": {
            "name": "massDestroy",
            "line": 148,
            "short_desc": "Delete all selected Product at once.",
            "long_desc": "",
            "hint": null,
            "hint_desc": null,
            "tags": [],
            "modifiers": 1,
            "is_by_ref": "",
            "exceptions": [],
            "errors": [],
            "parameters": {
                "request": {
                    "name": "request",
                    "line": 148,
                    "short_desc": "",
                    "long_desc": null,
                    "hint": [
                        [
                            "\\Illuminate\\Http\\Request",
                            false
                        ]
                    ],
                    "tags": [],
                    "modifiers": {
                        "nodeType": "Name_FullyQualified",
                        "parts": [
                            "Illuminate",
                            "Http",
                            "Request"
                        ],
                        "attributes": {
                            "startLine": 148,
                            "endLine": 148
                        }
                    },
                    "default": null,
                    "variadic": false,
                    "is_by_ref": false
                }
            }
        },
        "restore": {
            "name": "restore",
            "line": 169,
            "short_desc": "Restore Product from storage.",
            "long_desc": "",
            "hint": [
                [
                    "\\Illuminate\\Http\\Response",
                    false
                ]
            ],
            "hint_desc": "",
            "tags": [],
            "modifiers": 1,
            "is_by_ref": "",
            "exceptions": [],
            "errors": [],
            "parameters": {
                "id": {
                    "name": "id",
                    "line": 169,
                    "short_desc": "",
                    "long_desc": null,
                    "hint": [
                        [
                            "int",
                            false
                        ]
                    ],
                    "tags": [],
                    "modifiers": null,
                    "default": null,
                    "variadic": false,
                    "is_by_ref": false
                }
            }
        },
        "perma_del": {
            "name": "perma_del",
            "line": 186,
            "short_desc": "Permanently delete Product from storage.",
            "long_desc": "",
            "hint": [
                [
                    "\\Illuminate\\Http\\Response",
                    false
                ]
            ],
            "hint_desc": "",
            "tags": [],
            "modifiers": 1,
            "is_by_ref": "",
            "exceptions": [],
            "errors": [],
            "parameters": {
                "id": {
                    "name": "id",
                    "line": 186,
                    "short_desc": "",
                    "long_desc": null,
                    "hint": [
                        [
                            "int",
                            false
                        ]
                    ],
                    "tags": [],
                    "modifiers": null,
                    "default": null,
                    "variadic": false,
                    "is_by_ref": false
                }
            }
        }
    },
    "constants": []
}